mcedu/__init__.py
mcedu/config.py
mcedu/discovery.py
mcedu/utils.py
mcedu/auth/__init__.py
mcedu/auth/edutoken.py
mcedu/auth/minecraft.py
mcedu/auth/msft.py
mcedu/auth/playfab.py
mcedu/auth/token.py
mcedu-0.0.1.dist-info/licenses/LICENSE
mcedu-0.0.1.dist-info/METADATA
mcedu-0.0.1.dist-info/WHEEL
mcedu-0.0.1.dist-info/top_level.txt
mcedu-0.0.1.dist-info/RECORD
