Metadata-Version: 2.4
Name: mcedu
Version: 0.0.1
Summary: Provides methods to query Minecraft Education's discovery API and to generate tokens.
Author: josef240
License: MIT License
Keywords: minecraft,mcedu,joincode,discovery,minecraft education,minecraft auth,bedrock
Classifier: License :: OSI Approved :: MIT License
Classifier: Programming Language :: Python
Classifier: Programming Language :: Python :: 3
Requires-Python: >=3.11
License-File: LICENSE
Requires-Dist: requests-oauthlib>=2.0.0
Requires-Dist: requests
Requires-Dist: jwt
Dynamic: license-file
